certifi_system_store_wrapper.pth
certifi_system_store_wrapper/__init__.py
certifi_system_store_wrapper/__main__.py
certifi_system_store_wrapper/_version.py
certifi_system_store_wrapper/bootstrap.py
certifi_system_store_wrapper/certificates.py
certifi_system_store_wrapper/certificates_linux.py
certifi_system_store_wrapper/certificates_macos.py
certifi_system_store_wrapper/certificates_win.py
certifi_system_store_wrapper/logger.py
certifi_system_store_wrapper/wrapper.py
certifi_system_store_wrapper-0.0.1.dev9.dist-info/LICENSE
certifi_system_store_wrapper-0.0.1.dev9.dist-info/METADATA
certifi_system_store_wrapper-0.0.1.dev9.dist-info/WHEEL
certifi_system_store_wrapper-0.0.1.dev9.dist-info/entry_points.txt
certifi_system_store_wrapper-0.0.1.dev9.dist-info/top_level.txt
certifi_system_store_wrapper-0.0.1.dev9.dist-info/RECORD
