Metadata-Version: 2.1
Name: certifi-system-store-wrapper
Version: 0.0.1.dev9
Summary: Certifi wrapper packege to use system certificates
Author-email: Yukio Obuchi <Yukio.Oobuchi@sony.com>
Classifier: Programming Language :: Python :: 3
Classifier: License :: OSI Approved :: Apache Software License
Classifier: Operating System :: OS Independent
Requires-Python: >=3.7
License-File: LICENSE
Requires-Dist: certifi
Requires-Dist: wrapt
Requires-Dist: wincertstore ; sys_platform == "win32"
